NewLifeUtils/ColorModule.py
NewLifeUtils/ExceptModule.py
NewLifeUtils/FileModule.py
NewLifeUtils/LoggerModule.py
NewLifeUtils/StringUtilModule.py
NewLifeUtils/UtilsModule.py
NewLifeUtils/__init__.py
NewLifeUtils-5.2.1.dist-info/LICENSE
NewLifeUtils-5.2.1.dist-info/METADATA
NewLifeUtils-5.2.1.dist-info/WHEEL
NewLifeUtils-5.2.1.dist-info/top_level.txt
NewLifeUtils-5.2.1.dist-info/RECORD
