Metadata-Version: 2.1
Name: NewLifeUtils
Version: 5.2.1
Summary: View changelog.txt at https://raw.githubusercontent.com/NewLife1324/NewLifeUtils-Dev/main/CHANGELOG.txt
Home-page: https://github.com/NewLife1324/NewLifeUtils-Dev
Author: New Life
Author-email: semechkagent@gmail.com
License: MIT
Platform: Windows
Requires-Dist: PyYAML (>=5.4)
Requires-Dist: requests (~=2.25.1)
